claude_mux_iterm/__init__.py
claude_mux_iterm/__main__.py
claude_mux_iterm/exceptions.py
claude_mux_iterm/iterm.py
claude_mux_iterm/messaging.py
claude_mux_iterm/models.py
claude_mux_iterm/server.py
claude_mux_iterm/session_registry.py
claude_mux_iterm-0.1.0.dist-info/METADATA
claude_mux_iterm-0.1.0.dist-info/WHEEL
claude_mux_iterm-0.1.0.dist-info/entry_points.txt
claude_mux_iterm-0.1.0.dist-info/licenses/LICENSE
claude_mux_iterm-0.1.0.dist-info/RECORD
