Metadata-Version: 2.4
Name: claude-mux-iterm
Version: 0.1.0
Summary: MCP server for inter-session communication between Claude Code sessions in iTerm2
Project-URL: Homepage, https://github.com/GrigoriLab/claude-mux-iterm
Project-URL: Repository, https://github.com/GrigoriLab/claude-mux-iterm
Project-URL: Issues, https://github.com/GrigoriLab/claude-mux-iterm/issues
Author: GrigoriLab
License-Expression: MIT
License-File: LICENSE
Keywords: ai,claude,claude-code,communication,iterm,iterm2,mcp
Classifier: Development Status :: 3 - Alpha
Classifier: Environment :: Console
Classifier: Intended Audience :: Developers
Classifier: License :: OSI Approved :: MIT License
Classifier: Operating System :: MacOS
Classifier: Programming Language :: Python :: 3
Classifier: Programming Language :: Python :: 3.10
Classifier: Programming Language :: Python :: 3.11
Classifier: Programming Language :: Python :: 3.12
Classifier: Topic :: Software Development :: Version Control :: Git
Requires-Python: >=3.10
Requires-Dist: mcp>=1.0.0
Requires-Dist: pydantic>=2.0.0
Provides-Extra: dev
Requires-Dist: mypy>=1.8.0; extra == 'dev'
Requires-Dist: pytest-asyncio>=0.23.0; extra == 'dev'
Requires-Dist: pytest-cov>=4.1.0; extra == 'dev'
Requires-Dist: pytest-mock>=3.12.0; extra == 'dev'
Requires-Dist: pytest>=8.0.0; extra == 'dev'
Requires-Dist: ruff>=0.1.0; extra == 'dev'
